{
  "Aadhar Number": [
    "1234 5678 9012",
    "5678 4321 8765",
    "9876 5432 1098",
    "3456 7890 1234",
    "1111 2222 3333",
    "4444 5555 6666",
    "7777 8888 9999",
    "2468 1357 8024",
    "9630 8524 7410",
    "1029 3847 5648",
    "5489 3021 7645",
    "6789 1234 5678",
    "8765 4321 2345",
    "9123 4567 8912",
    "6543 2109 8765",
    "1111 2222 3333",
    "4444 5555 6666",
    "7777 8888 9999",
    "1234 4321 5678",
    "8765 2109 6543",
    "1357 2468 9753",
    "2468 1357 8642",
    "9090 8080 7070",
    "3214 5678 4321",
    "1597 3579 7531",
    "9753 8642 7531",
    "2020 3030 4040",
    "6060 7070 8080",
    "5050 4040 3030",
    "1122 3344 5566"
  ],
  "User Name": [
    "Rohit Vinay Sharma",
    "Ananya Gupta",
    "Vikram Mehul Mehta",
    "Priya Nair",
    "Siddhant Sushilkumar Indave",
    "Aarav Khanna",
    "Kavya Vishnu Reddy",
    "Manoj Patil",
    "Ishita Rajesh Verma",
    "Karan Malhotra",
    "Pooja Rajendra Desai",
    "Aditya Joshi",
    "Meera Kumar Pillai",
    "Rajesh Kumar",
    "Sneha Vishesh Kulkarni",
    "Rahul Sharma",
    "Priya Karun Nair",
    "Amit Patel",
    "Sneha Tushar Kapoor",
    "Vikram Desai",
    "Meera Vishesh Joshi",
    "Arjun Verma",
    "Ananya Karan Gupta",
    "Sandeep Mehta",
    "Kiran Brijesh Reddy",
    "Neha Bhatia",
    "Rajesh Sanman Kumar",
    "Divya Singh",
    "Kunal Arjun Malhotra",
    "Pooja Chauhan"
  ],
  "Date of Issue": [
    "01/01/2015",
    "23-05-2016",
    "14 Aug 2017",
    "2018-12-25",
    "02/02/2019",
    "30-06-2020",
    "2021/11/19",
    "15 July 2022",
    "04/04/2023",
    "29-09-2021",
    "10 Jan 2018",
    "2020-03-15",
    "18/08/2022",
    "05-11-2019",
    "12 Dec 2016",
    "01/01/2018",
    "12/11/2019",
    "23-07-2017",
    "05-03-2020",
    "2016-09-14",
    "2021-04-30",
    "10 Aug 2015",
    "15 Sep 2016",
    "02 Jan 2022",
    "28/02/2014",
    "17-06-2013",
    "2009-12-01",
    "2012-05-15",
    "19 Nov 2010",
    "22 Jul 2008"
    
  ],
  "PAN Number": [
    "ABCDE1234F",
    "PLMKJ6789Q",
    "QWERT4321P",
    "ZXCVB0987N",
    "ASDFG1122H",
    "MNOPQ7654K",
    "LKHGF2233D",
    "POIUY6677E",
    "TGBNH4455M",
    "VFRTY1123N",
    "WQASE9876J",
    "ZXMNB3322P",
    "KJHGF9001R",
    "QAZWS3456Y",
    "ABCDE1234F",
    "PQRSX6789Z",
    "LMNOP3456Q",
    "XYZAB9876C",
    "QWERT1234Y",
    "ZXCVB6789T",
    "ASDFG3456K",
    "HJKLP9876M",
    "TYUIO1234B",
    "GHJKL6789V",
    "BNMOP3456R",
    "ERTYU9876L",
    "CVBNM1234P",
    "LKJHG6789S",
    "MNBVC3456D"
  ],
  "Driver's License Number": [
    "MH14 20220012345",
    "DL01 20190067890",
    "KA05 20181234567",
    "GJ18 20174567890",
    "UP32 20189999999",
    "TN10 20176654321",
    "RJ14 20214561234",
    "HR26 20227654321",
    "BR01 20173334444",
    "PB08 20185555666",
    "WB20 20227778888",
    "KL07 20198887777",
    "TS09 20176667777",
    "CH01 20201112222",
    "JH05 20197776666",
    "MH12 20130012345",
    "DL05 20160054321",
    "KA01 20190067890",
    "GJ18 20210011223",
    "UP32 20150099887",
    "TN14 20140076543",
    "RJ20 20120033445",
    "WB24 20170055667",
    "KL07 20200077889",
    "HR26 20180099112",
    "MP09 20110022334",
    "BR01 20130044556",
    "CH03 20160066778",
    "OD19 20220088990",
    "PB10 20230011224"
  ],
  "Address": [
    "Flat 203, Green Valley Apartments, Andheri East, Mumbai - 400069",
    "12B, MG Road, Near Metro Station, Bengaluru - 560001",
    "H.No. 45, Sector 18, Dwarka, New Delhi - 110075",
    "Plot No. 9, Banjara Hills, Hyderabad - 500034",
    "33, Park Street, 2nd Floor, Kolkata - 700016",
    "D-11, Shastri Nagar, Jaipur - 302016",
    "House No. 76, Patel Colony, Ahmedabad - 380015",
    "23, VIP Road, Zirakpur, Chandigarh - 140603",
    "C-89, Indiranagar, Lucknow - 226016",
    "201, Rajendra Nagar, Patna - 800016",
    "15, Civil Lines, Nagpur - 440001",
    "9th Main, Koramangala, Bengaluru - 560034",

    "A-45, Model Town, Ludhiana - 141002",
    "Near ISBT, Sector 43, Chandigarh - 160036",
    "Plot No. 101, Anna Nagar, Chennai - 600040",
    "123, MG Road, Pune, Maharashtra",
    "45/2, Nehru Street, Chennai, Tamil Nadu",
    "Flat 201, Green Valley Apartments, Hyderabad",
    "Plot 56, Sector 18, Noida, Uttar Pradesh",
    "78, Park Lane, Kolkata, West Bengal",
    "House 34, Patel Nagar, New Delhi",
    "19, Gandhi Chowk, Jaipur, Rajasthan",
    "7th Floor, Tech Towers, Bengaluru",
    "22, Shivaji Marg, Lucknow, Uttar Pradesh",
    "Flat 12B, Lotus Residency, Ahmedabad, Gujarat",
    "3/45, Mission Road, Bhopal, Madhya Pradesh",
    "House 78, Rani Bagh, Nagpur, Maharashtra",
    "Villa 21, Palm Meadows, Kochi, Kerala",
    "56, Cantonment Area, Chandigarh",
    "9th Cross, Indiranagar, Bengaluru"
  ]
}
